pygenai_security/__init__.py
pygenai_security/setup.py
pygenai_security/analytics/__init__.py
pygenai_security/api/__init__.py
pygenai_security/cli/__init__.py
pygenai_security/cli/cli.py
pygenai_security/cli/minimal_cli.py
pygenai_security/core/__init__.py
pygenai_security/core/config_manager.py
pygenai_security/core/exceptions.py
pygenai_security/core/security_scanner.py
pygenai_security/core/vulnerability.py
pygenai_security/enterprise/__init__.py
pygenai_security/enterprise/license_manager.py
pygenai_security/integrations/__init__.py
pygenai_security/scanners/__init__.py
pygenai_security/scanners/configuration_scanner.py
pygenai_security/scanners/dependency_scanner.py
pygenai_security/scanners/genai_scanner.py
pygenai_security/scanners/traditional_scanner.py
pygenai_security/utils/__init__.py
pygenai_security/utils/logger.py
pygenai_security/utils/report_generator.py
pygenai_security-0.0.4.dist-info/licenses/LICENSE
pysecure_enterprise/__init__.py
pysecure_enterprise/analytics/__init__.py
pysecure_enterprise/analytics/compliance_reporting.py
pysecure_enterprise/analytics/enterprise_telemetry.py
pysecure_enterprise/analytics/roi_calculator.py
pysecure_enterprise/analytics/usage_analytics.py
pysecure_enterprise/api/__init__.py
pysecure_enterprise/api/auth_middleware.py
pysecure_enterprise/api/enterprise_api.py
pysecure_enterprise/api/rate_limiter.py
pysecure_enterprise/api/webhook_handler.py
pysecure_enterprise/cli/__init__.py
pysecure_enterprise/cli/admin_commands.py
pysecure_enterprise/cli/deployment_tools.py
pysecure_enterprise/cli/enterprise_cli.py
pysecure_enterprise/core/__init__.py
pysecure_enterprise/core/compliance_checker.py
pysecure_enterprise/core/enterprise_config.py
pysecure_enterprise/core/genai_security_analyzer.py
pysecure_enterprise/core/security_engine.py
pysecure_enterprise/core/threat_intelligence.py
pysecure_enterprise/core/vulnerability_manager.py
pysecure_enterprise/enterprise/__init__.py
pysecure_enterprise/enterprise/audit_logger.py
pysecure_enterprise/enterprise/enterprise_features.py
pygenai_security-0.0.4.dist-info/METADATA
pygenai_security-0.0.4.dist-info/WHEEL
pygenai_security-0.0.4.dist-info/entry_points.txt
pygenai_security-0.0.4.dist-info/top_level.txt
pygenai_security-0.0.4.dist-info/RECORD
