Metadata-Version: 2.4
Name: pygenai-security
Version: 0.0.4
Summary: Comprehensive Python and GenAI security scanning framework
Home-page: https://github.com/RiteshGenAI/pygenai-security
Author: RiteshGenAI
Author-email: riteshpatilgenaiofficial@gmail.com
License: MIT
Project-URL: Bug Reports, https://github.com/RiteshGenAI/pygenai-security/issues
Project-URL: Documentation, https://pygenai-security.readthedocs.io/
Project-URL: Source, https://github.com/RiteshGenAI/pygenai-security
Project-URL: Funding, https://github.com/sponsors/RiteshGenAI
Keywords: security,vulnerability,scanning,python,genai,llm,static-analysis,code-analysis,cybersecurity,devsecops,ai-security,prompt-injection,enterprise,compliance
Platform: any
Classifier: Development Status :: 5 - Production/Stable
Classifier: Intended Audience :: Developers
Classifier: Intended Audience :: Information Technology
Classifier: Intended Audience :: System Administrators
Classifier: License :: OSI Approved :: MIT License
Classifier: Operating System :: OS Independent
Classifier: Programming Language :: Python :: 3
Classifier: Programming Language :: Python :: 3.8
Classifier: Programming Language :: Python :: 3.9
Classifier: Programming Language :: Python :: 3.10
Classifier: Programming Language :: Python :: 3.11
Classifier: Programming Language :: Python :: 3.12
Classifier: Topic :: Security
Classifier: Topic :: Software Development :: Quality Assurance
Classifier: Topic :: Software Development :: Testing
Classifier: Topic :: Software Development :: Libraries :: Python Modules
Classifier: Topic :: System :: Systems Administration
Classifier: Environment :: Console
Classifier: Environment :: Web Environment
Requires-Python: >=3.8
License-File: LICENSE
Requires-Dist: click<9.0.0,>=8.0.0
Requires-Dist: pyyaml<7.0.0,>=6.0
Requires-Dist: requests<3.0.0,>=2.28.0
Requires-Dist: colorama<1.0.0,>=0.4.4
Requires-Dist: rich<14.0.0,>=12.0.0
Requires-Dist: jinja2<4.0.0,>=3.0.0
Requires-Dist: pathlib2>=2.3.0; python_version < "3.4"
Provides-Extra: dev
Requires-Dist: pytest>=7.0.0; extra == "dev"
Requires-Dist: pytest-cov>=4.0.0; extra == "dev"
Requires-Dist: pytest-asyncio>=0.21.0; extra == "dev"
Requires-Dist: black>=22.0.0; extra == "dev"
Requires-Dist: flake8>=5.0.0; extra == "dev"
Requires-Dist: mypy>=1.0.0; extra == "dev"
Requires-Dist: pre-commit>=2.20.0; extra == "dev"
Requires-Dist: tox>=3.25.0; extra == "dev"
Provides-Extra: enterprise
Requires-Dist: pygls>=1.0.0; extra == "enterprise"
Requires-Dist: lsprotocol>=2023.0.0; extra == "enterprise"
Requires-Dist: fastapi>=0.100.0; extra == "enterprise"
Requires-Dist: uvicorn>=0.20.0; extra == "enterprise"
Requires-Dist: sqlalchemy>=2.0.0; extra == "enterprise"
Requires-Dist: alembic>=1.12.0; extra == "enterprise"
Provides-Extra: docs
Requires-Dist: mkdocs>=1.4.0; extra == "docs"
Requires-Dist: mkdocs-material>=8.0.0; extra == "docs"
Requires-Dist: mkdocs-mermaid2-plugin>=0.6.0; extra == "docs"
Provides-Extra: all
Requires-Dist: pytest>=7.0.0; extra == "all"
Requires-Dist: pytest-cov>=4.0.0; extra == "all"
Requires-Dist: pytest-asyncio>=0.21.0; extra == "all"
Requires-Dist: black>=22.0.0; extra == "all"
Requires-Dist: flake8>=5.0.0; extra == "all"
Requires-Dist: mypy>=1.0.0; extra == "all"
Requires-Dist: pygls>=1.0.0; extra == "all"
Requires-Dist: lsprotocol>=2023.0.0; extra == "all"
Requires-Dist: fastapi>=0.100.0; extra == "all"
Requires-Dist: uvicorn>=0.20.0; extra == "all"
Requires-Dist: mkdocs>=1.4.0; extra == "all"
Requires-Dist: mkdocs-material>=8.0.0; extra == "all"
Dynamic: author
Dynamic: author-email
Dynamic: classifier
Dynamic: description
Dynamic: description-content-type
Dynamic: home-page
Dynamic: keywords
Dynamic: license
Dynamic: license-file
Dynamic: platform
Dynamic: project-url
Dynamic: provides-extra
Dynamic: requires-dist
Dynamic: requires-python
Dynamic: summary
